schwab/__init__.py
schwab/auth.py
schwab/debug.py
schwab/streaming.py
schwab/utils.py
schwab/version.py
schwab/client/__init__.py
schwab/client/asynchronous.py
schwab/client/base.py
schwab/client/synchronous.py
schwab/contrib/__init__.py
schwab/contrib/orders.py
schwab/contrib/util.py
schwab/orders/__init__.py
schwab/orders/common.py
schwab/orders/equities.py
schwab/orders/generic.py
schwab/orders/options.py
schwab/scripts/__init__.py
schwab/scripts/orders_codegen.py
schwab_py-1.5.0.data/scripts/schwab-generate-token.py
schwab_py-1.5.0.data/scripts/schwab-order-codegen.py
tests/__init__.py
tests/auth_test.py
tests/client_test.py
tests/debug_test.py
tests/orders_test.py
tests/streaming_test.py
tests/test.py
tests/utils.py
tests/utils_test.py
tests/contrib/__init__.py
tests/contrib/orders_test.py
tests/contrib/util_test.py
tests/orders/__init__.py
tests/orders/common_test.py
tests/orders/generic_test.py
tests/orders/options_test.py
tests/scripts/__init__.py
tests/scripts/orders_codegen_test.py
schwab_py-1.5.0.dist-info/LICENSE
schwab_py-1.5.0.dist-info/METADATA
schwab_py-1.5.0.dist-info/WHEEL
schwab_py-1.5.0.dist-info/top_level.txt
schwab_py-1.5.0.dist-info/RECORD
