Metadata-Version: 2.1
Name: schwab-py
Version: 1.5.0
Summary: Unofficial API wrapper for the Schwab HTTP API
Home-page: https://github.com/alexgolec/schwab-py
Author: Alex Golec
Author-email: bottomless.septic.tank@gmail.com
License: MIT
Project-URL: Documentation, https://schwab-py.readthedocs.io/en/latest/
Project-URL: Source, https://github.com/alexgolec/schwab-py
Project-URL: Tracker, https://github.com/alexgolec/schwab-py/issues
Keywords: finance trading equities bonds options research
Classifier: Programming Language :: Python :: 3
Classifier: License :: OSI Approved :: MIT License
Classifier: Operating System :: OS Independent
Classifier: Intended Audience :: Developers
Classifier: Development Status :: 1 - Planning
Classifier: Natural Language :: English
Classifier: Operating System :: OS Independent
Classifier: Topic :: Office/Business :: Financial :: Investment
Requires-Python: >=3.10
License-File: LICENSE
Requires-Dist: autopep8
Requires-Dist: authlib
Requires-Dist: flask
Requires-Dist: httpx
Requires-Dist: multiprocess
Requires-Dist: psutil
Requires-Dist: python-dateutil
Requires-Dist: urllib3
Requires-Dist: websockets
Provides-Extra: dev
Requires-Dist: callee; extra == "dev"
Requires-Dist: colorama; extra == "dev"
Requires-Dist: coverage; extra == "dev"
Requires-Dist: nose; extra == "dev"
Requires-Dist: pytest; extra == "dev"
Requires-Dist: pytz; extra == "dev"
Requires-Dist: setuptools; extra == "dev"
Requires-Dist: sphinx_rtd_theme; extra == "dev"
Requires-Dist: twine; extra == "dev"
Requires-Dist: wheel; extra == "dev"
